{
    "2015": [
        [
            "JavaScript",
            6702
        ],
        [
            "ООП",
            5146
        ],
        [
            "jQuery",
            5121
        ],
        [
            "HTML5",
            5003
        ],
        [
            "HTML",
            3791
        ],
        [
            "C#",
            3439
        ],
        [
            "MVC",
            3147
        ],
        [
            ".NET Framework",
            3116
        ],
        [
            "CSS",
            3015
        ],
        [
            "ASP.NET",
            2998
        ],
        [
            "PHP",
            2765
        ],
        [
            "Git",
            2528
        ],
        [
            "Ведение переговоров",
            2434
        ],
        [
            "MySQL",
            2430
        ],
        [
            "Java",
            2312
        ],
        [
            "SQL",
            2148
        ],
        [
            "Управление проектами",
            1977
        ],
        [
            "Поиск и привлечение клиентов",
            1868
        ],
        [
            "CSS3",
            1807
        ],
        [
            "Английский язык",
            1732
        ]
    ],
    "2016": [
        [
            "JavaScript",
            13481
        ],
        [
            "HTML",
            9790
        ],
        [
            "PHP",
            8995
        ],
        [
            "Git",
            8450
        ],
        [
            "Ведение переговоров",
            8407
        ],
        [
            "CSS",
            8136
        ],
        [
            "jQuery",
            7684
        ],
        [
            "MySQL",
            7591
        ],
        [
            "Работа в команде",
            7109
        ],
        [
            "HTML5",
            6756
        ],
        [
            "Пользователь ПК",
            6727
        ],
        [
            "SQL",
            6567
        ],
        [
            "Java",
            6431
        ],
        [
            "Управление проектами",
            6358
        ],
        [
            "ООП",
            6024
        ],
        [
            "Грамотная речь",
            5500
        ],
        [
            "CSS3",
            5356
        ],
        [
            "Поиск и привлечение клиентов",
            5286
        ],
        [
            "Навыки продаж",
            5123
        ],
        [
            "Активные продажи",
            5051
        ]
    ],
    "2017": [
        [
            "JavaScript",
            20170
        ],
        [
            "HTML",
            14485
        ],
        [
            "PHP",
            12682
        ],
        [
            "CSS",
            12672
        ],
        [
            "Git",
            12584
        ],
        [
            "MySQL",
            11175
        ],
        [
            "Ведение переговоров",
            10196
        ],
        [
            "SQL",
            9936
        ],
        [
            "jQuery",
            9708
        ],
        [
            "HTML5",
            8939
        ],
        [
            "Управление проектами",
            8723
        ],
        [
            "Java",
            8414
        ],
        [
            "Работа в команде",
            8173
        ],
        [
            "Linux",
            7952
        ],
        [
            "ООП",
            7917
        ],
        [
            "Пользователь ПК",
            7210
        ],
        [
            "Английский язык",
            6897
        ],
        [
            "Активные продажи",
            6871
        ],
        [
            "CSS3",
            6583
        ],
        [
            "B2B Продажи",
            6432
        ]
    ],
    "2018": [
        [
            "JavaScript",
            28103
        ],
        [
            "HTML",
            20174
        ],
        [
            "Git",
            19460
        ],
        [
            "CSS",
            17615
        ],
        [
            "PHP",
            17147
        ],
        [
            "SQL",
            16130
        ],
        [
            "MySQL",
            15693
        ],
        [
            "Ведение переговоров",
            15266
        ],
        [
            "Управление проектами",
            13631
        ],
        [
            "Работа в команде",
            13214
        ],
        [
            "Java",
            12965
        ],
        [
            "Linux",
            12440
        ],
        [
            "Пользователь ПК",
            11593
        ],
        [
            "HTML5",
            11423
        ],
        [
            "jQuery",
            11319
        ],
        [
            "Английский язык",
            10910
        ],
        [
            "Активные продажи",
            10246
        ],
        [
            "Грамотная речь",
            9865
        ],
        [
            "ООП",
            9799
        ],
        [
            "Деловая переписка",
            9634
        ]
    ],
    "2019": [
        [
            "JavaScript",
            31635
        ],
        [
            "SQL",
            25629
        ],
        [
            "Git",
            25126
        ],
        [
            "HTML",
            22114
        ],
        [
            "Работа в команде",
            20011
        ],
        [
            "Английский язык",
            19672
        ],
        [
            "CSS",
            19579
        ],
        [
            "Пользователь ПК",
            18710
        ],
        [
            "Linux",
            18152
        ],
        [
            "Ведение переговоров",
            18092
        ],
        [
            "Управление проектами",
            17962
        ],
        [
            "PHP",
            17461
        ],
        [
            "Java",
            17120
        ],
        [
            "MySQL",
            16144
        ],
        [
            "Грамотная речь",
            15902
        ],
        [
            "Python",
            14710
        ],
        [
            "Активные продажи",
            12489
        ],
        [
            "ООП",
            11553
        ],
        [
            "Деловая переписка",
            11237
        ],
        [
            "B2B Продажи",
            11158
        ]
    ],
    "2020": [
        [
            "SQL",
            56764
        ],
        [
            "Git",
            45503
        ],
        [
            "Английский язык",
            43439
        ],
        [
            "JavaScript",
            41325
        ],
        [
            "Работа в команде",
            39109
        ],
        [
            "Пользователь ПК",
            37616
        ],
        [
            "Linux",
            36571
        ],
        [
            "Грамотная речь",
            33868
        ],
        [
            "Java",
            30722
        ],
        [
            "HTML",
            28078
        ],
        [
            "Python",
            28048
        ],
        [
            "Управление проектами",
            27749
        ],
        [
            "CSS",
            25497
        ],
        [
            "Активные продажи",
            23285
        ],
        [
            "MS SQL",
            23197
        ],
        [
            "MySQL",
            22498
        ],
        [
            "PostgreSQL",
            21947
        ],
        [
            "Ведение переговоров",
            21111
        ],
        [
            "PHP",
            20950
        ],
        [
            "ООП",
            17799
        ]
    ],
    "2021": [
        [
            "Работа в команде",
            96440
        ],
        [
            "SQL",
            96414
        ],
        [
            "Английский язык",
            86388
        ],
        [
            "Грамотная речь",
            77188
        ],
        [
            "Git",
            74292
        ],
        [
            "Пользователь ПК",
            62068
        ],
        [
            "JavaScript",
            58612
        ],
        [
            "Linux",
            57973
        ],
        [
            "Управление проектами",
            51195
        ],
        [
            "Python",
            49883
        ],
        [
            "Java",
            42782
        ],
        [
            "HTML",
            37996
        ],
        [
            "PostgreSQL",
            36148
        ],
        [
            "Ведение переговоров",
            35476
        ],
        [
            "Adobe Photoshop",
            33654
        ],
        [
            "CSS",
            32957
        ],
        [
            "Грамотность",
            32913
        ],
        [
            "Деловое общение",
            31639
        ],
        [
            "Активные продажи",
            30765
        ],
        [
            "MS SQL",
            30582
        ]
    ],
    "2022": [
        [
            "Работа в команде",
            92410
        ],
        [
            "SQL",
            89842
        ],
        [
            "Английский язык",
            70608
        ],
        [
            "Git",
            67732
        ],
        [
            "Linux",
            57900
        ],
        [
            "Пользователь ПК",
            53027
        ],
        [
            "Грамотная речь",
            47851
        ],
        [
            "Python",
            47809
        ],
        [
            "JavaScript",
            45648
        ],
        [
            "Управление проектами",
            45076
        ],
        [
            "PostgreSQL",
            37245
        ],
        [
            "Adobe Photoshop",
            35129
        ],
        [
            "Java",
            34042
        ],
        [
            "Техническое обслуживание",
            29310
        ],
        [
            "MS PowerPoint",
            27896
        ],
        [
            "1С программирование",
            27307
        ],
        [
            "HTML",
            26745
        ],
        [
            "Аналитическое мышление",
            26679
        ],
        [
            "Грамотность",
            25886
        ],
        [
            "PHP",
            25686
        ]
    ],
    "2023": [
        [
            "SQL",
            62368
        ],
        [
            "Работа в команде",
            45313
        ],
        [
            "Linux",
            41049
        ],
        [
            "Git",
            37744
        ],
        [
            "Python",
            35688
        ],
        [
            "Грамотная речь",
            31817
        ],
        [
            "PostgreSQL",
            30432
        ],
        [
            "Пользователь ПК",
            28205
        ],
        [
            "Английский язык",
            27032
        ],
        [
            "Управление проектами",
            26447
        ],
        [
            "JavaScript",
            25351
        ],
        [
            "Аналитическое мышление",
            24417
        ],
        [
            "Adobe Photoshop",
            24374
        ],
        [
            "1С программирование",
            22154
        ],
        [
            "Работа с большим объемом информации",
            21448
        ],
        [
            "Java",
            20731
        ],
        [
            "Техническая поддержка",
            18770
        ],
        [
            "Деловое общение",
            18464
        ],
        [
            "PHP",
            18091
        ],
        [
            "Docker",
            17949
        ]
    ],
    "2024": [
        [
            "SQL",
            48119
        ],
        [
            "Linux",
            29619
        ],
        [
            "Python",
            27281
        ],
        [
            "Git",
            23616
        ],
        [
            "PostgreSQL",
            23539
        ],
        [
            "Аналитическое мышление",
            20174
        ],
        [
            "Техническая поддержка",
            18671
        ],
        [
            "JavaScript",
            16223
        ],
        [
            "Работа с большим объемом информации",
            15652
        ],
        [
            "Настройка ПК",
            15547
        ],
        [
            "Английский язык",
            15191
        ],
        [
            "Java",
            15155
        ],
        [
            "Adobe Photoshop",
            15042
        ],
        [
            "Работа в команде",
            14681
        ],
        [
            "1С программирование",
            14533
        ],
        [
            "Грамотная речь",
            14349
        ],
        [
            "Docker",
            14168
        ],
        [
            "Пользователь ПК",
            13547
        ],
        [
            "Деловая коммуникация",
            13370
        ],
        [
            "Информационные технологии",
            12837
        ]
    ]
}